EduRPA/__init__.py
EduRPA/Google/Classroom.py
EduRPA/Google/CustomOAuth.py
EduRPA/Google/Form.py
EduRPA/Google/Utils.py
EduRPA/Google/__init__.py
EduRPA/Storage/S3Storage.py
EduRPA/Storage/Storage.py
EduRPA/Storage/__init__.py
edurpa_cloud-0.0.5.dist-info/LICENSE
edurpa_cloud-0.0.5.dist-info/METADATA
edurpa_cloud-0.0.5.dist-info/WHEEL
edurpa_cloud-0.0.5.dist-info/top_level.txt
edurpa_cloud-0.0.5.dist-info/RECORD
